MANIFEST.in
README.rst
requirements.txt
setup.py
hive_email_job.egg-info/PKG-INFO
hive_email_job.egg-info/SOURCES.txt
hive_email_job.egg-info/dependency_links.txt
hive_email_job.egg-info/requires.txt
hive_email_job.egg-info/top_level.txt
hiveemailjob/__init__.py
hiveemailjob/main.py
hiveemailjob/settings.py