Metadata-Version: 1.1
Name: hive-email-job
Version: 2.1.1
Summary: Use Python implements get data from Hive then send attachments to user.
Home-page: https://github.com/elkan1788/HiveEmailJob
Author: elkan1788
Author-email: elkan1788@gmail.com
License: Apache License V2.0
Platform: UNKNOWN
Classifier: Development Status :: 4 - Beta
Classifier: Operating System :: OS Independent
Classifier: Intended Audience :: Developers
Classifier: License :: OSI Approved :: Apache Software License
Classifier: Natural Language :: Chinese (Simplified)
Classifier: Natural Language :: English
Classifier: Programming Language :: Python
Classifier: Programming Language :: Python :: Implementation
Classifier: Programming Language :: Python :: 2
Classifier: Programming Language :: Python :: 2.6
Classifier: Programming Language :: Python :: 2.7
Classifier: Topic :: Software Development :: Libraries
